lps22hh/__init__.py
lps22hh/lps22hh.py
lps22hh/register.py
lps22hh-1.0.0.dist-info/licenses/LICENSE
lps22hh-1.0.0.dist-info/METADATA
lps22hh-1.0.0.dist-info/WHEEL
lps22hh-1.0.0.dist-info/top_level.txt
lps22hh-1.0.0.dist-info/RECORD
