Metadata-Version: 2.4
Name: lps22hh
Version: 1.0.0
Summary: Raspberry Pi Pico Micropyhton library to interact with the ST LPS22HH or LPS27HH Barometric pressure sensor
Author-email: Chris Braissant <chrisbraissant@gmail.com>
License: MIT License
Project-URL: Repository, https://github.com/cbraissant/lps22hh-pico-driver
Classifier: Development Status :: 3 - Alpha
Classifier: Operating System :: OS Independent
Classifier: License :: OSI Approved :: MIT License
Classifier: Intended Audience :: Developers
Classifier: Programming Language :: Python :: 3
Classifier: Programming Language :: Python :: 3.11
Classifier: Topic :: Software Development :: Embedded Systems
Requires-Python: >=3.8
License-File: LICENSE
Dynamic: license-file
